veracity_authz/__init__.py
veracity_authz/cedar_client.py
veracity_authz/cedarpy_engine.py
veracity_authz/context_builder.py
veracity_authz/exceptions.py
veracity_authz/policy_loader.py
veracity_authz/types.py
veracitylabauthz-0.2.0.dist-info/METADATA
veracitylabauthz-0.2.0.dist-info/WHEEL
veracitylabauthz-0.2.0.dist-info/top_level.txt
veracitylabauthz-0.2.0.dist-info/RECORD
