Metadata-Version: 2.4
Name: veracityLabAuthZ
Version: 0.2.0
Summary: Shared Cedar authorization helpers for Veracity services.
Author: Veracity Lab
Classifier: Programming Language :: Python :: 3
Classifier: Operating System :: OS Independent
Requires-Python: >=3.10
Provides-Extra: cedarpy
Requires-Dist: cedarpy<5.0,>=4.8; extra == "cedarpy"
